README.md
VERSION
setup.py
apian.egg-info/PKG-INFO
apian.egg-info/SOURCES.txt
apian.egg-info/dependency_links.txt
apian.egg-info/requires.txt
apian.egg-info/top_level.txt
src/apian/__init__.py
src/apian/api.py
src/apian/app.py
src/apian/auth.py
src/apian/config.py
src/apian/meta.py