Metadata-Version: 1.1
Name: apian
Version: 0.2.4
Summary: 
Home-page: https://gitlab.com/greenhousegroup/ai/libraries/apian/
Author: Greenhouse AI team
Author-email: ai@greenhousegroup.com
License: UNKNOWN
Keywords: rest http web
Platform: UNKNOWN
Classifier: Programming Language :: Python :: 3
Classifier: License :: OSI Approved :: MIT License
Classifier: Operating System :: OS Independent
Classifier: Programming Language :: Python :: 3
